chainexplorer
