Metadata-Version: 2.1
Name: chainexplorer
Version: 0.0.1
Summary: Quickly retrieve and explore Bitcoin blocks
Home-page: https://github.com/akcarsten/chain_explorer
Author: Carsten Klein
Author-email: 
License: MIT License
Classifier: Programming Language :: Python :: 3
Classifier: License :: OSI Approved :: MIT License
Classifier: Operating System :: OS Independent
Requires-Python: >=3.8
License-File: LICENSE
